setup.py
hellodepils/__init__.py
hellodepils.egg-info/PKG-INFO
hellodepils.egg-info/SOURCES.txt
hellodepils.egg-info/dependency_links.txt
hellodepils.egg-info/not-zip-safe
hellodepils.egg-info/top_level.txt