Metadata-Version: 1.0
Name: hellodepils
Version: 0.1
Summary: The funniest joke in the world
Home-page: http://github.com/daugapvils/hellodepils
Author: SV
Author-email: daugavpils@gmail.com
License: MIT
Platform: UNKNOWN
